optic/__init__.py
optic/main.py
optic_sdk-0.1.0.dist-info/WHEEL
optic_sdk-0.1.0.dist-info/METADATA
optic_sdk-0.1.0.dist-info/RECORD
