Metadata-Version: 2.1
Name: optic-sdk
Version: 0.1.0
Summary: Python SDK for Optic
Home-page: https://github.com/silentninja/optic-python
License: MIT
Keywords: swagger,optic,sdk,api
Author: Mukesh
Author-email: mmukesh95@hotmail.com
Requires-Python: >=3.7,<4.0
Classifier: Environment :: Console
Classifier: Framework :: Flake8
Classifier: License :: OSI Approved :: MIT License
Classifier: Operating System :: OS Independent
Classifier: Programming Language :: Python :: 3
Classifier: Programming Language :: Python :: 3.7
Classifier: Programming Language :: Python :: 3.8
Classifier: Programming Language :: Python :: 3.9
Classifier: Topic :: Software Development :: Documentation
Classifier: Topic :: Software Development :: Libraries :: Python Modules
Classifier: Topic :: Software Development :: Quality Assurance
Requires-Dist: requests (>=2.26.0,<3.0.0)
Project-URL: Repository, https://github.com/silentninja/optic-python/sdk
